{
  "session_id": "session-118",
  "phase_id": "phase6",
  "title": "正本 failure_type 分類の精緻化（誤分類補正と regression の正本化）",
  "goal": "error_message・stop_stage・各チェック出力を結合した診断文脈から、JSON 欠損・禁止パス・init 段の preflight 重複などが test_failure に誤分類されないよう spec_missing / scope_violation / regression に振り分ける。regression_detected フラグは breaking_change ではなく regression にマップする。成功セッションの report フィールドを壊さない。",
  "scope": [
    "orchestration/run_session.py の FAILURE_TYPE_PRIORITY_ORDER / VALID_FAILURE_TYPES への regression 追加",
    "診断テキスト集約とヒューリスティック（_aggregate_diagnostic_text / _heuristic_failure_from_report_context）",
    "resolve_canonical_failure_type / classify_failure の error_message・stop_stage オプション引数と分岐順序",
    "build_failure_record_for_report / persist_session_reports からの canonical 解決への文脈引き渡し",
    "上記契約を検証する backend/tests/test_failure_type_priority.py と backend/tests/test_report_generation.py の追補"
  ],
  "out_of_scope": [
    "retry ループ全体の設計変更",
    "providers / config.yaml の変更",
    "patch apply context mismatch 専用ロジックの新規大改修（別セッションで扱う）",
    "breaking_change を完全削除すること（後方互換のため残す）"
  ],
  "constraints": [
    "1セッション1目的を厳守し、failure_type 正本分類の補正のみに限定する",
    "既存の優先順位（patch / build / import / typecheck / lint+test の基本順）を崩さない",
    "ヒューリスティックは型付きチャネル判定の後段で適用し、実際の pytest 失敗は test_failure のまま残す",
    "省略時は従来どおり error_message / stop_stage なしで動作すること（既存呼び出し互換）"
  ],
  "acceptance_ref": "docs/acceptance/session-118.yaml",
  "allowed_changes": [
    "orchestration/run_session.py",
    "backend/tests/test_failure_type_priority.py",
    "backend/tests/test_report_generation.py"
  ],
  "allowed_changes_detail": [
    "orchestration/run_session.py: regression 正本値の追加、診断集約・文脈ヒューリスティック、resolve_canonical_failure_type / classify_failure の kwargs、report 経路への文脈連携、fingerprint / failure_layer への regression 反映",
    "backend/tests/test_failure_type_priority.py: spec_missing / scope_violation / regression / 実テスト失敗の AC テスト",
    "backend/tests/test_report_generation.py: 成功系 report が再分類後も壊れないことの回帰テスト"
  ],
  "forbidden_changes": [
    "orchestration/providers/",
    "docs/sessions/ の session-118.json 以外の既存セッション定義の無関係な改変",
    "docs/acceptance/ の session-118.yaml 以外の無関係な改変",
    ".github/",
    "orchestration/config.yaml",
    "Card_task_02 側アプリケーションファイル"
  ],
  "completion_criteria": [
    {
      "id": "CC-118-01",
      "type": "behavior_contract",
      "condition": "JSON 欠損系メッセージは spec_missing に分類される"
    },
    {
      "id": "CC-118-02",
      "type": "behavior_contract",
      "condition": "禁止パス検出メッセージは scope_violation に分類される"
    },
    {
      "id": "CC-118-03",
      "type": "behavior_contract",
      "condition": "init 段の preflight 重複定義は regression に分類される"
    },
    {
      "id": "CC-118-04",
      "type": "non_regression",
      "condition": "AssertionError / ModuleNotFoundError 等の実テスト・import 失敗は test_failure / import_error のまま"
    },
    {
      "id": "CC-118-05",
      "type": "artifact",
      "condition": "status=success の report に失敗系メタデータが混入しない"
    }
  ],
  "acceptance_criteria": [
    {
      "id": "AC-118-01",
      "text": "JSON 欠損メッセージは test_failure に落とさず spec_missing とする",
      "test_name": "test_resolve_canonical_failure_type_prefers_spec_missing_for_missing_json",
      "completion_criteria_refs": ["CC-118-01"]
    },
    {
      "id": "AC-118-02",
      "text": "禁止パス検出は test_failure ではなく scope_violation とする",
      "test_name": "test_resolve_canonical_failure_type_prefers_scope_violation_for_forbidden_path",
      "completion_criteria_refs": ["CC-118-02"]
    },
    {
      "id": "AC-118-03",
      "text": "init 段の preflight 重複定義は regression とする",
      "test_name": "test_resolve_canonical_failure_type_prefers_regression_for_init_preflight_duplicate",
      "completion_criteria_refs": ["CC-118-03"]
    },
    {
      "id": "AC-118-04",
      "text": "実際の pytest / import 失敗は test_failure / import_error のまま維持する",
      "test_name": "test_resolve_canonical_failure_type_keeps_real_test_failures_as_test_failure",
      "completion_criteria_refs": ["CC-118-04"]
    },
    {
      "id": "AC-118-05",
      "text": "failure_type 再分類後も成功系 report の failure 系フィールドを壊さない",
      "test_name": "test_report_generation_preserves_success_cases_after_failure_type_reclassification",
      "completion_criteria_refs": ["CC-118-05"]
    }
  ],
  "review_points": [
    "ヒューリスティックが高優先チャネル判定と矛盾しない順序になっているか",
    "kwargs 省略時の後方互換",
    "成功パスの report 破壊がないか"
  ]
}
